tweedekamer/__init__.py
tweedekamer/debate.py
tweedekamer/search.py
tweedekamer/speach.py
tweedekamer/speaker.py
tweedekamer/subtitle.py
tweedekamer/video.py
tweedekamer/enums/debate_type.py
tweedekamer/enums/sort_direction.py
tweedekamer/enums/sort_type.py
tweedekamer-0.1.3.dist-info/METADATA
tweedekamer-0.1.3.dist-info/WHEEL
tweedekamer-0.1.3.dist-info/top_level.txt
tweedekamer-0.1.3.dist-info/RECORD
