Metadata-Version: 2.1
Name: tweedekamer
Version: 0.1.3
Summary: A package to download Dutch parliament debates and subtitles
Home-page: https://github.com/micheldore/tweedekamer
Author: Michel Doré
Author-email: 
